robotlib/__init__.py
robotlib/adapter/__init__.py
robotlib/adapter/airtest.py
robotlib/asettings/__init__.py
robotlib/asettings/config.ini
robotlib/asettings/settings.py
robotlib/assertion/__init__.py
robotlib/assertion/assert_bicv.py
robotlib/assertion/assert_config.py
robotlib/assertion/assert_factory.py
robotlib/base/__init__.py
robotlib/base/singleton.py
robotlib/can/__init__.py
robotlib/can/can_dev.py
robotlib/can/can_dev_config.py
robotlib/can/can_dev_factory.py
robotlib/common/__init__.py
robotlib/common/common_path.py
robotlib/graphic/__init__.py
robotlib/graphic/recognize/__init__.py
robotlib/graphic/recognize/core/__init__.py
robotlib/graphic/recognize/core/cv.py
robotlib/graphic/recognize/core/error.py
robotlib/graphic/recognize/core/helper.py
robotlib/graphic/recognize/core/settings.py
robotlib/graphic/recognize/robotcv/__init__.py
robotlib/graphic/recognize/robotcv/cal_confidence.py
robotlib/graphic/recognize/robotcv/error.py
robotlib/graphic/recognize/robotcv/keypoint_base.py
robotlib/graphic/recognize/robotcv/keypoint_matching.py
robotlib/graphic/recognize/robotcv/keypoint_matching_contrib.py
robotlib/graphic/recognize/robotcv/multiscale_template_matching.py
robotlib/graphic/recognize/robotcv/robotcv.py
robotlib/graphic/recognize/robotcv/screen_recorder.py
robotlib/graphic/recognize/robotcv/sift.py
robotlib/graphic/recognize/robotcv/template.py
robotlib/graphic/recognize/robotcv/template_matching.py
robotlib/graphic/recognize/robotcv/utils.py
robotlib/graphic/recognize/utils/__init__.py
robotlib/graphic/recognize/utils/logger.py
robotlib/graphic/recognize/utils/logwraper.py
robotlib/graphic/recognize/utils/resolution.py
robotlib/graphic/recognize/utils/snippet.py
robotlib/graphic/recognize/utils/transform.py
robotlib/init/__init__.py
robotlib/init/init.py
robotlib/log/__init__.py
robotlib/log/log.py
robotlib/log/log_config.py
robotlib/notification/__init__.py
robotlib/notification/notification.py
robotlib/notification/notification_config.py
bicv_robotlib-0.0.36.dist-info/METADATA
bicv_robotlib-0.0.36.dist-info/WHEEL
bicv_robotlib-0.0.36.dist-info/top_level.txt
bicv_robotlib-0.0.36.dist-info/RECORD
