Metadata-Version: 2.1
Name: bicv-robotlib
Version: 0.0.36
Summary: 基于三分类的中文情感分析
Author: toney_xzw
Author-email: bhnw <bhshare.cn@gmail.com>
Project-URL: Homepage, https://github.com/yaokui2018
Project-URL: Bug Tracker, https://github.com/yaokui2018/bhsenti/issues
Classifier: Programming Language :: Python :: 3
Classifier: License :: OSI Approved :: GNU General Public License v3 (GPLv3)
Classifier: Operating System :: OS Independent
Requires-Python: >=3
Requires-Dist: transformers >=4.27.1
Requires-Dist: onnxruntime
